pycfdi_credentials/__init__.py
pycfdi_credentials/algorithms.py
pycfdi_credentials/certificate.py
pycfdi_credentials/private_key.py
pycfdi_credentials/utils.py
pycfdi_credentials-1.5.0.dist-info/licenses/LICENSE
pycfdi_credentials-1.5.0.dist-info/METADATA
pycfdi_credentials-1.5.0.dist-info/WHEEL
pycfdi_credentials-1.5.0.dist-info/top_level.txt
pycfdi_credentials-1.5.0.dist-info/RECORD
