Metadata-Version: 2.4
Name: pycfdi_credentials
Version: 1.5.0
Summary: Library to manage CSD and FIEL files from SAT. Use this to sign, verify and get certificate data.
Author-email: Moises Navarro <moisalejandro@gmail.com>
License-Expression: LGPL-2.1
Requires-Python: >=3.12
License-File: LICENSE
Requires-Dist: pyopenssl>=25.1.0
Dynamic: license-file
